projectcompactor/__init__.py
projectcompactor/cli.py
projectcompactor-6.9421.dist-info/LICENSE
projectcompactor-6.9421.dist-info/METADATA
projectcompactor-6.9421.dist-info/WHEEL
projectcompactor-6.9421.dist-info/entry_points.txt
projectcompactor-6.9421.dist-info/top_level.txt
projectcompactor-6.9421.dist-info/RECORD
