Metadata-Version: 2.1
Name: projectcompactor
Version: 6.9421
Summary: A powerful, user-friendly Python tool to generate project trees and file contents (with MIME detection).
Home-page: https://github.com/yourusername/projectcompactor
Author: veppy
Author-email: vonepern@gmail.com.com
License: UNKNOWN
Platform: UNKNOWN
Classifier: Programming Language :: Python :: 3
Classifier: Operating System :: OS Independent
Classifier: License :: OSI Approved :: MIT License
Requires-Python: >=3.6
License-File: LICENSE
Requires-Dist: tqdm (>=4.0.0)
Requires-Dist: python-magic (>=0.4.15)
